taeg/__init__.py
taeg/test_taeg.py
taeg-1.0.1.dist-info/LICENSE
taeg-1.0.1.dist-info/METADATA
taeg-1.0.1.dist-info/WHEEL
taeg-1.0.1.dist-info/top_level.txt
taeg-1.0.1.dist-info/RECORD
