Metadata-Version: 2.1
Name: taeg
Version: 1.0.1
Summary: Calcul du taux annuel effectif global
Home-page: https://github.com/ThbtSprt/taeg
Author: Thibaut Spriet
Author-email: thibaut@spriet.online
License: UNKNOWN
Project-URL: Bug Tracker, https://github.com/ThbtSprt/taeg/issues
Platform: UNKNOWN
Classifier: Programming Language :: Python :: 3
Classifier: License :: OSI Approved :: MIT License
Classifier: Operating System :: OS Independent
Requires-Python: >=3.6
License-File: LICENSE
Requires-Dist: frdate
Requires-Dist: dateutils
